{
  "w": 852,
  "h": 1136,
  "img_myp_base_large": {
    "file": "ui/mypage/myp_base_large",
    "type": "image",
    "x": 78,
    "y": -22,
    "z": 1,
    "w": 694,
    "h": 1178
  },
  "img_news_base": {
    "file": "common/com_dialog_header.png",
    "type": "image",
    "x": 133,
    "y": 1020,
    "z": 2,
    "w": 586,
    "h": 88
  },
  "pat_btn_ok": {
    "file": "common/btn_01",
    "type": "part",
    "x": 290,
    "y": 32,
    "z": 3,
    "w": 270,
    "h": 90
  },
  "img_base_green_edge": {
    "scale": 0.95,
    "height": 960,
    "style": "dialog_green_line_edge",
    "file": "common/com_base_green_line_edge",
    "type": "image",
    "x": 102,
    "y": 100,
    "z": 4,
    "w": 650,
    "h": 960
  },
  "img_line_green_short": {
    "file": "common/com_line_short",
    "type": "image",
    "x": 121,
    "y": 911,
    "z": 5,
    "w": 608,
    "h": 40
  },
  "img_tag_orange": {
    "file": "common/com_tag_orange",
    "type": "image",
    "x": 147,
    "y": 950,
    "z": 6,
    "w": 110,
    "h": 50
  },
  "font_title": {
    "style": "text_subtitle_left",
    "text": "お知らせタイトルです",
    "type": "label",
    "x": 258,
    "y": 967,
    "z": 7,
    "w": 466,
    "h": 31
  },
  "part_btn_back": {
    "file": "common/btn_02",
    "type": "part",
    "x": 143,
    "y": 144,
    "z": 8,
    "w": 180,
    "h": 90
  },
  "font_title_01": {
    "valign": "center",
    "align": "center",
    "color": "fdfa45",
    "italic": false,
    "type": "label",
    "text": "お知らせ",
    "style": "text_title",
    "x": 146,
    "y": 1036,
    "z": 9,
    "w": 560,
    "h": 56
  },
  "table_list": {
    "vautoadjust": "up",
    "direction": "vertical",
    "cellheight": 68,
    "cellwidth": 570,
    "cell": "mypage/myp_news_detail_content_01",
    "type": "table",
    "x": 142,
    "y": 238,
    "z": 10,
    "w": 570,
    "h": 676
  }
}
