{
  "w": 640,
  "h": 400,
  "img_bg": {
    "file": "character/chara_info_base",
    "type": "image",
    "x": 0,
    "y": 1,
    "z": 1,
    "w": 640,
    "h": 397
  },
  "img_sp_atk_bg": {
    "width": 519,
    "style": "text_value_bg_02",
    "file": "common/com_text_value_11",
    "type": "image",
    "x": 111,
    "y": 94,
    "z": 2,
    "w": 519,
    "h": 70
  },
  "font_sp_atk_detail": {
    "text": "必殺技の説明七八九十一二三四五六七八九十一",
    "marquee": true,
    "italic": true,
    "style": "text_normal_left",
    "type": "label",
    "x": 123,
    "y": 93,
    "z": 3,
    "w": 483,
    "h": 36
  },
  "font_sp_atk": {
    "text": "必殺技の名前七八九十一二三四五六七八九十",
    "size": 18,
    "marquee": true,
    "italic": true,
    "style": "text_normal_left",
    "type": "label",
    "x": 131,
    "y": 126,
    "z": 4,
    "w": 402,
    "h": 36
  },
  "font_sp_atk_icon": {
    "text": "必殺技の名前七八九十一二三四五六七八九十",
    "size": 18,
    "marquee": true,
    "italic": true,
    "style": "text_normal_left",
    "type": "label",
    "x": 159,
    "y": 126,
    "z": 5,
    "w": 371,
    "h": 36
  },
  "img_sp_skill_icon": {
    "scale": 0.3,
    "file": "master/outgame/extension/character_detail/sp_skill_icon_01.png",
    "type": "image",
    "x": 126,
    "y": 126,
    "z": 6,
    "w": 39,
    "h": 36
  },
  "part_btn": {
    "file": "common/btn_10",
    "type": "part",
    "x": 534,
    "y": 127,
    "z": 7,
    "w": 81,
    "h": 34
  },
  "img_label_sp_atk_lv": {
    "file": "common/label/com_label_sp_atk_lv_05",
    "type": "image",
    "x": 6,
    "y": 129,
    "z": 8,
    "w": 98,
    "h": 28
  },
  "img_base_splv": {
    "file": "common/com_text_value_sp",
    "type": "image",
    "x": 9,
    "y": 101,
    "z": 9,
    "w": 80,
    "h": 30
  },
  "font_sp_atk_lv": {
    "text": "99",
    "style": "text_normal_left",
    "size": 18,
    "italic": true,
    "align": "right",
    "valign": "bottom",
    "type": "label",
    "x": 11,
    "y": 105,
    "z": 10,
    "w": 35,
    "h": 36
  },
  "font_sp_atk_maxlv": {
    "text": "/99",
    "size": 14,
    "style": "text_normal_left",
    "italic": true,
    "valign": "bottom",
    "type": "label",
    "x": 45,
    "y": 105,
    "z": 11,
    "w": 45,
    "h": 36
  },
  "img_skill_bg": {
    "width": 512,
    "style": "text_value_bg",
    "file": "common/com_text_value",
    "type": "image",
    "x": 115,
    "y": 171,
    "z": 12,
    "w": 512,
    "h": 40
  },
  "font_leader_skill": {
    "text": "リーダースキルの名前一二三四五六七八九十一二",
    "marquee": true,
    "italic": true,
    "style": "text_normal_left",
    "type": "label",
    "x": 133,
    "y": 172,
    "z": 13,
    "w": 477,
    "h": 36
  },
  "img_label_leader_skill": {
    "file": "common/label/com_label_leader_skill",
    "type": "image",
    "x": 10,
    "y": 171,
    "z": 14,
    "w": 120,
    "h": 40
  },
  "img_label_cost": {
    "file": "ui/common/label/com_label_yellow_cost",
    "type": "image",
    "x": 552,
    "y": 237,
    "z": 15,
    "w": 79,
    "h": 40
  },
  "font_cost": {
    "text": "99",
    "font": "FOT-NewRodinProN-EB.otf",
    "align": "center",
    "size": 24,
    "style": "text_normal_right",
    "italic": true,
    "type": "label",
    "x": 559,
    "y": 215,
    "z": 16,
    "w": 62,
    "h": 31
  },
  "img_label_lv": {
    "file": "common/label/com_label_large_lv",
    "type": "image",
    "x": -13,
    "y": 213,
    "z": 17,
    "w": 100,
    "h": 40
  },
  "font_lv": {
    "text": "100",
    "style": "text_normal",
    "italic": true,
    "font": "FOT-NewRodinProN-EB.otf",
    "size": 31,
    "align": "right",
    "type": "label",
    "x": 108,
    "y": 214,
    "z": 18,
    "w": 77,
    "h": 44
  },
  "font_max_lv": {
    "text": "/100",
    "font": "FOT-NewRodinProN-EB.otf",
    "size": 21,
    "style": "text_normal_left",
    "italic": true,
    "type": "label",
    "x": 186,
    "y": 213,
    "z": 19,
    "w": 77,
    "h": 36
  },
  "img_gauge_base": {
    "width": 300,
    "style": "progress_bar_base",
    "file": "character/cha_gauge_large_base",
    "type": "image",
    "x": 255,
    "y": 221,
    "z": 20,
    "w": 299,
    "h": 20
  },
  "gauge_exp": {
    "file": "character/cha_gauge_large_long",
    "direction": "horizontal",
    "type": "progress",
    "x": 263,
    "y": 223,
    "z": 21,
    "w": 294,
    "h": 16
  },
  "font_next_exp": {
    "text": "999999",
    "size": 24,
    "style": "text_normal_left",
    "font": "FOT-NewRodinProN-EB.otf",
    "italic": true,
    "type": "label",
    "x": 418,
    "y": 242,
    "z": 22,
    "w": 62,
    "h": 31
  },
  "img_label_next_level": {
    "file": "ui/common/label/com_label_yellow_next_lv",
    "type": "image",
    "x": 280,
    "y": 236,
    "z": 23,
    "w": 140,
    "h": 40
  },
  "part_hp": {
    "scale": 0.95,
    "file": "charactermenu/cha_detail/chara_info_status",
    "type": "part",
    "x": 4,
    "y": 278,
    "z": 24,
    "w": 225,
    "h": 105
  },
  "part_atk": {
    "scale": 0.95,
    "file": "charactermenu/cha_detail/chara_info_status",
    "type": "part",
    "x": 206,
    "y": 278,
    "z": 25,
    "w": 225,
    "h": 105
  },
  "part_def": {
    "file": "charactermenu/cha_detail/chara_info_status",
    "scale": 0.95,
    "type": "part",
    "x": 409,
    "y": 278,
    "z": 26,
    "w": 225,
    "h": 105
  }
}
