{
  "w": 178,
  "h": 64,
  "fla_button": {
    "normal": "common/btn/com_btn_17_green",
    "selected": "common/btn/com_btn_17_green",
    "anime_selected": "ef_017",
    "lwf_file": "outgame/effect/btn_00000/btn_00000.lwf",
    "type": "flashbutton",
    "x": 0,
    "y": 0,
    "z": 1,
    "w": 178,
    "h": 64
  },
  "font_sort_text": {
    "text": "お気に入り",
    "scale": 0.7,
    "kerning": -3,
    "style": "text_button",
    "font": "btn_normal.fnt",
    "type": "bmlabel",
    "x": 19,
    "y": 10,
    "z": 2,
    "w": 138,
    "h": 44
  }
}
