{
  "w": 640,
  "h": 600,
  "img_dialog_base": {
    "style": "dialog1",
    "height": 595,
    "file": "common/com_dialog",
    "type": "image",
    "x": 5,
    "y": 4,
    "z": 1,
    "w": 630,
    "h": 593
  },
  "parts_btn": {
    "file": "common/btn_01",
    "type": "part",
    "x": 325,
    "y": 26,
    "z": 2,
    "w": 270,
    "h": 90
  },
  "parts_btn2": {
    "file": "common/btn_01",
    "type": "part",
    "x": 46,
    "y": 26,
    "z": 3,
    "w": 270,
    "h": 90
  },
  "parts_btn3": {
    "file": "common/btn_01",
    "type": "part",
    "x": 191,
    "y": 26,
    "z": 4,
    "w": 270,
    "h": 90
  },
  "font_no_stone": {
    "text": "：50 龍石",
    "style": "text_normal_left",
    "type": "label",
    "x": 310,
    "y": 355,
    "z": 5,
    "w": 286,
    "h": 36
  },
  "font_no_stone2": {
    "text": "1回",
    "style": "text_normal_orange_italic",
    "align": "right",
    "font": "FOT-NewRodinProN-EB.otf",
    "type": "label",
    "x": 45,
    "y": 355,
    "z": 6,
    "w": 230,
    "h": 36
  },
  "font_no_stone3": {
    "text": "：5 龍石",
    "style": "text_normal_left",
    "type": "label",
    "x": 310,
    "y": 314,
    "z": 7,
    "w": 286,
    "h": 36
  },
  "font_no_stone4": {
    "text": "所持龍石",
    "style": "text_normal_orange_italic",
    "align": "right",
    "font": "FOT-NewRodinProN-EB.otf",
    "type": "label",
    "x": 45,
    "y": 314,
    "z": 8,
    "w": 230,
    "h": 36
  },
  "font_no_stone5": {
    "text": "：DOKKANフェスコイン",
    "style": "text_normal_left",
    "type": "label",
    "x": 310,
    "y": 255,
    "z": 9,
    "w": 286,
    "h": 36
  },
  "font_no_stone6": {
    "text": "獲得できるコイン",
    "style": "text_normal_orange_italic",
    "align": "right",
    "font": "FOT-NewRodinProN-EB.otf",
    "type": "label",
    "x": 45,
    "y": 255,
    "z": 10,
    "w": 230,
    "h": 36
  },
  "font_no_stone7": {
    "text": "：10 個",
    "style": "text_normal_left",
    "type": "label",
    "x": 310,
    "y": 214,
    "z": 11,
    "w": 286,
    "h": 36
  },
  "font_no_stone8": {
    "text": "個数",
    "style": "text_normal_orange_italic",
    "align": "right",
    "font": "FOT-NewRodinProN-EB.otf",
    "type": "label",
    "x": 45,
    "y": 214,
    "z": 12,
    "w": 230,
    "h": 36
  },
  "font_text": {
    "text": "龍石が足りません",
    "style": "text_normal_caution_italic",
    "type": "label",
    "x": 46,
    "y": 133,
    "z": 13,
    "w": 550,
    "h": 58
  },
  "font_text_top": {
    "text": "text",
    "style": "text_normal",
    "type": "label",
    "x": 46,
    "y": 421,
    "z": 14,
    "w": 550,
    "h": 69
  },
  "font_title": {
    "text": "R確定10連ガシャ",
    "style": "text_title",
    "valign": "top",
    "type": "label",
    "x": 46,
    "y": 514,
    "z": 15,
    "w": 550,
    "h": 36
  }
}
