{
  "w": 640,
  "h": 1536,
  "img_bg": {
    "height": 1536,
    "file": "ui/common/com_bg_dim",
    "type": "image",
    "x": -106,
    "y": -5,
    "z": 1,
    "w": 852,
    "h": 1545
  },
  "img_bg2": {
    "file": "ui/common/com_bg_dim",
    "height": 1536,
    "type": "image",
    "x": -106,
    "y": -16,
    "z": 2,
    "w": 852,
    "h": 1568
  },
  "part_btn_ok": {
    "file": "common/btn_01",
    "type": "part",
    "x": 184,
    "y": 230,
    "z": 3,
    "w": 270,
    "h": 90
  },
  "font_text_top": {
    "valign": "top",
    "align": "center",
    "type": "label",
    "style": "text_normal",
    "text": "文字列が長すぎるか\n不正な文字が含まれています\n\nお問い合わせ番号:",
    "x": 59,
    "y": 662,
    "z": 4,
    "w": 522,
    "h": 173
  },
  "font_title": {
    "type": "label",
    "text": "ERROR",
    "style": "text_title",
    "align": "center",
    "color": "ff0000",
    "x": 45,
    "y": 868,
    "z": 5,
    "w": 550,
    "h": 35
  }
}
