{
  "w": 640,
  "h": 1136,
  "img_bg": {
    "file": "gasha/gas_scouter_bg",
    "type": "image",
    "x": 0,
    "y": 270,
    "z": 1,
    "w": 640,
    "h": 850
  },
  "img_bg_mask": {
    "file": "gasha/gas_scouter_bg_mask",
    "type": "image",
    "x": 6,
    "y": 274,
    "z": 2,
    "w": 630,
    "h": 221
  },
  "page_place_selected": {
    "direction": "horizontal",
    "cell": "gasha/gasha_scouter_info",
    "type": "page",
    "x": 0,
    "y": 271,
    "z": 3,
    "w": 640,
    "h": 850
  },
  "img_scouter_frame": {
    "file": "gasha/gas_scouter_frame",
    "type": "image",
    "x": 0,
    "y": 270,
    "z": 4,
    "w": 640,
    "h": 852
  },
  "pagegauge": {
    "selected": "common/com_ui_ball_active",
    "normal": "common/com_ui_ball_disabled",
    "direction": "horizontal",
    "type": "pagegauge",
    "x": 282,
    "y": 229,
    "z": 5,
    "w": 76,
    "h": 20
  },
  "fla_arrow_left": {
    "linkage": "",
    "file": "",
    "selected": "common/com_empty_50x40",
    "normal": "common/com_empty_50x40",
    "anime_normal": "ef_004",
    "lwf_file": "outgame/effect/anim_100000/anim_100000.lwf",
    "type": "flashbutton",
    "x": 15,
    "y": 224,
    "z": 6,
    "w": 42,
    "h": 31
  },
  "fla_arrow_right": {
    "linkage": "",
    "file": "",
    "rotate": 180,
    "selected": "common/com_empty_50x40",
    "normal": "common/com_empty_50x40",
    "anime_normal": "ef_004",
    "lwf_file": "outgame/effect/anim_100000/anim_100000.lwf",
    "type": "flashbutton",
    "x": 583,
    "y": 223,
    "z": 7,
    "w": 42,
    "h": 31
  },
  "img_base_text": {
    "file": "gasha/gas_base_text",
    "type": "image",
    "x": 6,
    "y": 65,
    "z": 8,
    "w": 627,
    "h": 151
  },
  "font_text": {
    "text": "スカウターに反応あり！\nピックアップキャラクターをチェック！",
    "style": "text_normal",
    "type": "label",
    "x": 46,
    "y": 104,
    "z": 9,
    "w": 546,
    "h": 96
  },
  "part_btn_back": {
    "file": "common/btn_02",
    "type": "part",
    "x": 10,
    "y": 7,
    "z": 10,
    "w": 173,
    "h": 73
  },
  "img_new": {
    "file": "common/com_new",
    "type": "image",
    "x": 25,
    "y": 1099,
    "z": 11,
    "w": 68,
    "h": 30
  }
}
